ApiTestFramework/CaseExecutor.py
ApiTestFramework/CodeGenerator.py
ApiTestFramework/SwaggerParser.py
ApiTestFramework/__init__.py
ApiTestFramework/atf_exec.py
ApiTestFramework-0.1.2.dist-info/METADATA
ApiTestFramework-0.1.2.dist-info/RECORD
ApiTestFramework-0.1.2.dist-info/WHEEL
ApiTestFramework-0.1.2.dist-info/entry_points.txt
ApiTestFramework-0.1.2.dist-info/top_level.txt
