Metadata-Version: 2.1
Name: ApiTestFramework
Version: 0.1.2
Summary: Api test framework in Linux
Home-page: https://github.com/seoktaehyeon/api-test-framework
Author: Will
Author-email: v.stone@163.com
Maintainer: Will
Maintainer-email: v.stone@163.com
License: MIT
Platform: linux
Requires-Dist: PyYAML (>=5.2)
Requires-Dist: requests (>=2.22.0)
Requires-Dist: pytest (>=5.3.2)
Requires-Dist: pytest-html (>=2.0.1)
